{
    "Document": {
        "@id": "0000093",
        "@source": "ADAM",
        "@url": "https://www.nlm.nih.gov/medlineplus/ency/article/002219.htm",
        "Focus": "Adrenal glands",
        "FocusAnnotations": {
            "Category": "Other"
        },
        "QAPairs": {
            "QAPair": {
                "@pid": "1",
                "Question": {
                    "@qid": "0000093-1",
                    "@qtype": "information",
                    "#text": "Do you have information about Adrenal glands"
                },
                "Answer": null
            }
        }
    }
}