{
    "Document": {
        "@id": "0001139",
        "@source": "ADAM",
        "@url": "https://www.nlm.nih.gov/medlineplus/ency/article/007631.htm",
        "Focus": "Dental crowns",
        "FocusAnnotations": {
            "Category": "Other",
            "Synonyms": {
                "Synonym": [
                    "Dental caps",
                    "Porcelain crowns",
                    "Lab-fabricated restoration"
                ]
            }
        },
        "QAPairs": {
            "QAPair": {
                "@pid": "1",
                "Question": {
                    "@qid": "0001139-1",
                    "@qtype": "information",
                    "#text": "Do you have information about Dental crowns"
                },
                "Answer": null
            }
        }
    }
}