{
    "Document": {
        "@id": "0001515",
        "@source": "ADAM",
        "@url": "https://www.nlm.nih.gov/medlineplus/ency/article/001425.htm",
        "Focus": "Facial nerve palsy due to birth trauma",
        "FocusAnnotations": {
            "Category": "Disease",
            "UMLS": {
                "CUIs": {
                    "CUI": [
                        "C0270104",
                        "C0262576"
                    ]
                },
                "SemanticTypes": {
                    "SemanticType": [
                        "T037",
                        "T047"
                    ]
                },
                "SemanticGroup": "Disorders"
            },
            "Synonyms": {
                "Synonym": "Seventh cranial nerve palsy due to birth trauma"
            }
        },
        "QAPairs": {
            "QAPair": [
                {
                    "@pid": "1",
                    "Question": {
                        "@qid": "0001515-1",
                        "@qtype": "information",
                        "#text": "What is (are) Facial nerve palsy due to birth trauma ?"
                    },
                    "Answer": null
                },
                {
                    "@pid": "2",
                    "Question": {
                        "@qid": "0001515-2",
                        "@qtype": "causes",
                        "#text": "What causes Facial nerve palsy due to birth trauma ?"
                    },
                    "Answer": null
                },
                {
                    "@pid": "3",
                    "Question": {
                        "@qid": "0001515-3",
                        "@qtype": "symptoms",
                        "#text": "What are the symptoms of Facial nerve palsy due to birth trauma ?"
                    },
                    "Answer": null
                },
                {
                    "@pid": "4",
                    "Question": {
                        "@qid": "0001515-4",
                        "@qtype": "exams and tests",
                        "#text": "How to diagnose Facial nerve palsy due to birth trauma ?"
                    },
                    "Answer": null
                },
                {
                    "@pid": "5",
                    "Question": {
                        "@qid": "0001515-5",
                        "@qtype": "treatment",
                        "#text": "What are the treatments for Facial nerve palsy due to birth trauma ?"
                    },
                    "Answer": null
                },
                {
                    "@pid": "6",
                    "Question": {
                        "@qid": "0001515-6",
                        "@qtype": "outlook",
                        "#text": "What is the outlook for Facial nerve palsy due to birth trauma ?"
                    },
                    "Answer": null
                },
                {
                    "@pid": "7",
                    "Question": {
                        "@qid": "0001515-7",
                        "@qtype": "complications",
                        "#text": "What are the complications of Facial nerve palsy due to birth trauma ?"
                    },
                    "Answer": null
                },
                {
                    "@pid": "8",
                    "Question": {
                        "@qid": "0001515-8",
                        "@qtype": "when to contact a medical professional",
                        "#text": "Do I need to see a doctor for Facial nerve palsy due to birth trauma ?"
                    },
                    "Answer": null
                },
                {
                    "@pid": "9",
                    "Question": {
                        "@qid": "0001515-9",
                        "@qtype": "prevention",
                        "#text": "How to prevent Facial nerve palsy due to birth trauma ?"
                    },
                    "Answer": null
                }
            ]
        }
    }
}