{
    "Document": {
        "@id": "0001117",
        "@source": "ADAM",
        "@url": "https://www.nlm.nih.gov/medlineplus/ency/patientinstructions/000384.htm",
        "Focus": "Defining overweight and obesity - children",
        "FocusAnnotations": {
            "Category": "Disease",
            "UMLS": {
                "CUIs": {
                    "CUI": [
                        "C0028754",
                        "C0497406"
                    ]
                },
                "SemanticTypes": {
                    "SemanticType": [
                        "T047",
                        "T184"
                    ]
                },
                "SemanticGroup": "Disorders"
            }
        },
        "QAPairs": {
            "QAPair": {
                "@pid": "1",
                "Question": {
                    "@qid": "0001117-1",
                    "@qtype": "information",
                    "#text": "What is (are) Defining overweight and obesity - children ?"
                },
                "Answer": null
            }
        }
    }
}