{
    "Document": {
        "@id": "0001387",
        "@source": "ADAM",
        "@url": "https://www.nlm.nih.gov/medlineplus/ency/article/003917.htm",
        "Focus": "Endometrial biopsy",
        "FocusAnnotations": {
            "Category": "Other",
            "Synonyms": {
                "Synonym": "Biopsy - endometrium"
            }
        },
        "QAPairs": {
            "QAPair": {
                "@pid": "1",
                "Question": {
                    "@qid": "0001387-1",
                    "@qtype": "information",
                    "#text": "Do you have information about Endometrial biopsy"
                },
                "Answer": null
            }
        }
    }
}