{
    "Document": {
        "@id": "0002135",
        "@source": "ADAM",
        "@url": "https://www.nlm.nih.gov/medlineplus/ency/patientinstructions/000074.htm",
        "Focus": "Ileostomy - discharge",
        "FocusAnnotations": {
            "Category": "Other",
            "Synonyms": {
                "Synonym": [
                    "Standard ileostomy - discharge",
                    "Brooke ileostomy - discharge",
                    "Continent ileostomy - discharge",
                    "Abdominal pouch - discharge",
                    "End ileostomy - discharge",
                    "Ostomy - discharge"
                ]
            }
        },
        "QAPairs": {
            "QAPair": {
                "@pid": "1",
                "Question": {
                    "@qid": "0002135-1",
                    "@qtype": "information",
                    "#text": "Do you have information about Ileostomy - discharge"
                },
                "Answer": null
            }
        }
    }
}