{
    "Document": {
        "@id": "0003034",
        "@source": "ADAM",
        "@url": "https://www.nlm.nih.gov/medlineplus/ency/patientinstructions/000461.htm",
        "Focus": "Peripherally inserted central catheter - insertion",
        "FocusAnnotations": {
            "Category": "Other",
            "Synonyms": {
                "Synonym": "PICC - insertion"
            }
        },
        "QAPairs": {
            "QAPair": {
                "@pid": "1",
                "Question": {
                    "@qid": "0003034-1",
                    "@qtype": "information",
                    "#text": "Do you have information about Peripherally inserted central catheter - insertion"
                },
                "Answer": null
            }
        }
    }
}