{
    "Document": {
        "@id": "0004040",
        "@source": "ADAM",
        "@url": "https://www.nlm.nih.gov/medlineplus/ency/article/001660.htm",
        "Focus": "Trisomy 13",
        "FocusAnnotations": {
            "Category": "Disease",
            "UMLS": {
                "CUIs": {
                    "CUI": [
                        "C0152095",
                        "C2936830"
                    ]
                },
                "SemanticTypes": {
                    "SemanticType": [
                        "T019",
                        "T049",
                        "T047"
                    ]
                },
                "SemanticGroup": "Disorders"
            },
            "Synonyms": {
                "Synonym": "Patau syndrome"
            }
        },
        "QAPairs": {
            "QAPair": [
                {
                    "@pid": "1",
                    "Question": {
                        "@qid": "0004040-1",
                        "@qtype": "information",
                        "#text": "What is (are) Trisomy 13 ?"
                    },
                    "Answer": null
                },
                {
                    "@pid": "2",
                    "Question": {
                        "@qid": "0004040-2",
                        "@qtype": "causes",
                        "#text": "What causes Trisomy 13 ?"
                    },
                    "Answer": null
                },
                {
                    "@pid": "3",
                    "Question": {
                        "@qid": "0004040-3",
                        "@qtype": "symptoms",
                        "#text": "What are the symptoms of Trisomy 13 ?"
                    },
                    "Answer": null
                },
                {
                    "@pid": "4",
                    "Question": {
                        "@qid": "0004040-4",
                        "@qtype": "exams and tests",
                        "#text": "How to diagnose Trisomy 13 ?"
                    },
                    "Answer": null
                },
                {
                    "@pid": "5",
                    "Question": {
                        "@qid": "0004040-5",
                        "@qtype": "treatment",
                        "#text": "What are the treatments for Trisomy 13 ?"
                    },
                    "Answer": null
                },
                {
                    "@pid": "6",
                    "Question": {
                        "@qid": "0004040-6",
                        "@qtype": "support groups",
                        "#text": "Where to find support for people with Trisomy 13 ?"
                    },
                    "Answer": null
                },
                {
                    "@pid": "7",
                    "Question": {
                        "@qid": "0004040-7",
                        "@qtype": "outlook",
                        "#text": "What is the outlook for Trisomy 13 ?"
                    },
                    "Answer": null
                },
                {
                    "@pid": "8",
                    "Question": {
                        "@qid": "0004040-8",
                        "@qtype": "complications",
                        "#text": "What are the complications of Trisomy 13 ?"
                    },
                    "Answer": null
                },
                {
                    "@pid": "9",
                    "Question": {
                        "@qid": "0004040-9",
                        "@qtype": "when to contact a medical professional",
                        "#text": "Do I need to see a doctor for Trisomy 13 ?"
                    },
                    "Answer": null
                },
                {
                    "@pid": "10",
                    "Question": {
                        "@qid": "0004040-10",
                        "@qtype": "prevention",
                        "#text": "How to prevent Trisomy 13 ?"
                    },
                    "Answer": null
                }
            ]
        }
    }
}